tree_shade_mapper/__init__.py
tree_shade_mapper/cli.py
tree_shade_mapper/image_process.py
tree_shade_mapper/solar_data_process.py
tree_shade_mapper/tree_shade_mapper.py
tree_shade_mapper/visualization.py
tree_shade_mapper-0.1.2.dist-info/AUTHORS.rst
tree_shade_mapper-0.1.2.dist-info/LICENSE
tree_shade_mapper-0.1.2.dist-info/METADATA
tree_shade_mapper-0.1.2.dist-info/WHEEL
tree_shade_mapper-0.1.2.dist-info/top_level.txt
tree_shade_mapper-0.1.2.dist-info/RECORD
