Metadata-Version: 2.2
Name: tree_shade_mapper
Version: 0.1.2
Summary: Python package to calculate the shading effect of tree canopies from panoramic imagery
Author-email: Kunihiko Fujiwara <kunihiko@nus.edu.sg>
Maintainer-email: Kunihiko Fujiwara <kunihiko@nus.edu.sg>
License: CC-BY-SA-4.0
Project-URL: bugs, https://github.com/{{ cookiecutter.github_username }}/{{ cookiecutter.project_slug }}/issues
Project-URL: changelog, https://github.com/{{ cookiecutter.github_username }}/{{ cookiecutter.project_slug }}/blob/master/changelog.md
Project-URL: homepage, https://github.com/{{ cookiecutter.github_username }}/{{ cookiecutter.project_slug }}
License-File: LICENSE
License-File: AUTHORS.rst
Requires-Dist: zensvi
Requires-Dist: typer
Requires-Dist: pandas
Requires-Dist: pvlib
Requires-Dist: folium
Requires-Dist: branca
Requires-Dist: h3
Requires-Dist: seaborn
Requires-Dist: geopandas
Requires-Dist: shapely
Requires-Dist: numpy
Requires-Dist: matplotlib
Requires-Dist: contextily
Requires-Dist: pillow
Requires-Dist: scipy
Requires-Dist: opencv-python
Requires-Dist: pytz
Requires-Dist: scikit-learn
Provides-Extra: dev
Requires-Dist: coverage; extra == "dev"
Requires-Dist: mypy; extra == "dev"
Requires-Dist: pytest; extra == "dev"
Requires-Dist: ruff; extra == "dev"
